[
 {
  "en-US": "Management Backend",
  "key": "menu.management",
  "zh-CN": "管理后台"
 },
 {
  "en-US": "Account Management",
  "key": "menu.management.account",
  "zh-CN": "账户管理"
 },
 {
  "en-US": "Role Management",
  "key": "menu.management.role",
  "zh-CN": "角色管理"
 },
 {
  "en-US": "Label Management",
  "key": "menu.management.defectLabel",
  "zh-CN": "标签管理"
 },
 {
  "en-US": "Service Monitoring",
  "key": "menu.serverMonitoring",
  "zh-CN": "服务监控"
 },
 {
  "en-US": "Model Center",
  "key": "menu.modelCenter",
  "zh-CN": "模型中心"
 },
 {
  "en-US": "Training Details",
  "key": "menu.modelCenter.trainingDetails",
  "zh-CN": "训练详情"
 },
 {
  "en-US": "Annotation Platform",
  "key": "menu.annotation",
  "zh-CN": "标注平台"
 },
 {
  "en-US": "Annotation Platform",
  "key": "menu.annotation.annotation",
  "zh-CN": "标注平台"
 },
 {
  "en-US": "Adjudication Station",
  "key": "menu.adjudicationStation",
  "zh-CN": "复判站"
 },
 {
  "en-US": "Data Management",
  "key": "menu.dataManagement",
  "zh-CN": "数据管理"
 },
 {
  "en-US": "Management List",
  "key": "menu.dataManagement.managementList",
  "zh-CN": "管理列表"
 },
 {
  "en-US": "Annotation List",
  "key": "menu.dataManagement.annotationList",
  "zh-CN": "标注列表"
 },
 {
  "en-US": "Audit List",
  "key": "menu.dataManagement.auditList",
  "zh-CN": "审核列表"
 },
 {
  "en-US": "Image List",
  "key": "menu.dataManagement.imageList",
  "zh-CN": "图片列表"
 },
 {
  "en-US": "Annotation Platform",
  "key": "menu.markPlatform",
  "zh-CN": "标注平台"
 },
 {
  "en-US": "Detection Template",
  "key": "menu.aoiTpl",
  "zh-CN": "检测模版"
 },
 {
  "en-US": "Template List",
  "key": "menu.aoiTpl.aoiTplList",
  "zh-CN": "模版列表"
 },
 {
  "en-US": "New Template",
  "key": "menu.aoiTpl.aoiTplNew",
  "zh-CN": "新建模版"
 },
 {
  "en-US": "Edit Template",
  "key": "menu.aoiTpl.aoiTplEdit",
  "zh-CN": "编辑模版"
 },
 {
  "en-US": "Golden Board Programming",
  "key": "menu.aoiTpl.boardProgramming",
  "zh-CN": "金板编程"
 },
 {
  "en-US": "Designer",
  "key": "menu.lowCode",
  "zh-CN": "设计器"
 }
]
